no_spark_in_my_home/__init__.py
no_spark_in_my_home/demo/__init__.py
no_spark_in_my_home/demo/book.py
no_spark_in_my_home/demo/user.py
no_spark_in_my_home/src/__init__.py
no_spark_in_my_home/src/generator.py
no_spark_in_my_home/src/handlers.py
no_spark_in_my_home-1.0.4.dist-info/METADATA
no_spark_in_my_home-1.0.4.dist-info/WHEEL
no_spark_in_my_home-1.0.4.dist-info/top_level.txt
no_spark_in_my_home-1.0.4.dist-info/RECORD
