Metadata-Version: 2.1
Name: no-spark-in-my-home
Version: 1.0.4
Summary: Yet another Python package for data generation
Author: nomilkinmyhome
Author-email: scripthound <grinkiko@gmail.com>
Project-URL: Homepage, https://github.com/NorthShine/datahack-test-data-generating
Keywords: fake,data,generator
Classifier: Programming Language :: Python
Classifier: Programming Language :: Python :: 3
Requires-Python: >=3.7
Requires-Dist: pyspark
Requires-Dist: pandas
Requires-Dist: mimesis
